farsi_faker/__init__.py
farsi_faker/_version.py
farsi_faker/faker.py
farsi_faker/data/__init__.py
farsi_faker/data/names.pkl
farsi_faker-1.0.0.dist-info/licenses/LICENSE
farsi_faker-1.0.0.dist-info/METADATA
farsi_faker-1.0.0.dist-info/WHEEL
farsi_faker-1.0.0.dist-info/top_level.txt
farsi_faker-1.0.0.dist-info/RECORD
