Metadata-Version: 2.4
Name: farsi-faker
Version: 1.0.0
Summary: Generate realistic fake Persian/Farsi names for testing - تولید اسم‌های فارسی فیک با 10,000+ اسم اصیل
Home-page: https://github.com/alisadeghiaghili/farsi-faker
Author: Ali Sadeghi Aghili
Author-email: Ali Sadeghi Aghili <alisadeghiaghili@gmail.com>
Maintainer: Ali Sadeghi Aghili
Maintainer-email: Ali Sadeghi Aghili <alisadeghiaghili@gmail.com>
License: MIT
Project-URL: Homepage, https://github.com/alisadeghiaghili/farsi-faker
Project-URL: Documentation, https://github.com/alisadeghiaghili/farsi-faker#readme
Project-URL: Repository, https://github.com/alisadeghiaghili/farsi-faker
Project-URL: Bug Tracker, https://github.com/alisadeghiaghili/farsi-faker/issues
Project-URL: Source Code, https://github.com/alisadeghiaghili/farsi-faker
Project-URL: Changelog, https://github.com/alisadeghiaghili/farsi-faker/releases
Keywords: persian-names,farsi-names,iranian-names,fake-data,test-data,mock-data,name-generator,data-generator,faker,farsi,persian,iranian,iran,names,generator,testing,mock,dataset,synthetic,sample,development,automation,fixtures,localization,i18n,middle-east,reproducible,lightweight,fast,فارسی,ایرانی,پارسی
Classifier: Development Status :: 5 - Production/Stable
Classifier: Intended Audience :: Developers
Classifier: Intended Audience :: Science/Research
Classifier: License :: OSI Approved :: MIT License
Classifier: Programming Language :: Python :: 3
Classifier: Programming Language :: Python :: 3.7
Classifier: Programming Language :: Python :: 3.8
Classifier: Programming Language :: Python :: 3.9
Classifier: Programming Language :: Python :: 3.10
Classifier: Programming Language :: Python :: 3.11
Classifier: Programming Language :: Python :: 3.12
Classifier: Programming Language :: Python :: 3.13
Classifier: Programming Language :: Python :: 3 :: Only
Classifier: Natural Language :: Persian
Classifier: Operating System :: OS Independent
Classifier: Topic :: Software Development :: Libraries :: Python Modules
Classifier: Topic :: Software Development :: Testing
Classifier: Topic :: Software Development :: Testing :: Mocking
Classifier: Topic :: Scientific/Engineering :: Information Analysis
Classifier: Typing :: Typed
Requires-Python: >=3.7
License-File: LICENSE
Provides-Extra: dev
Requires-Dist: pytest>=7.0.0; extra == "dev"
Requires-Dist: pytest-cov>=4.0.0; extra == "dev"
Requires-Dist: pandas>=1.3.0; extra == "dev"
Dynamic: author
Dynamic: home-page
Dynamic: license-file
Dynamic: maintainer
Dynamic: requires-python
